plotbitrate.py
frame/__init__.py
frame/_frame_class.py
frame/_frame_dataclass.py
plotbitrate-1.1.3.0.dist-info/LICENSE
plotbitrate-1.1.3.0.dist-info/METADATA
plotbitrate-1.1.3.0.dist-info/WHEEL
plotbitrate-1.1.3.0.dist-info/entry_points.txt
plotbitrate-1.1.3.0.dist-info/top_level.txt
plotbitrate-1.1.3.0.dist-info/RECORD
