Metadata-Version: 2.1
Name: plotbitrate
Version: 1.1.3.0
Summary: A simple bitrate plotter for media files
Home-page: https://github.com/zeroepoch/plotbitrate
Author: Eric Work
Author-email: work.eric@gmail.com
License: BSD
Keywords: ffprobe bitrate plot
Classifier: Topic :: Multimedia :: Sound/Audio
Classifier: Natural Language :: English
Classifier: Programming Language :: Python :: 3
Requires-Python: >=3.6
License-File: LICENSE
Requires-Dist: matplotlib
Requires-Dist: pyqt6
